qsnctf/__init__.py
qsnctf/api.py
qsnctf/auxiliary.py
qsnctf/base.py
qsnctf/crypto.py
qsnctf/cvecodepy.py
qsnctf/hash.py
qsnctf/math.py
qsnctf/misc.py
qsnctf/web.py
qsnctf/plugin/js/aaencode.js
qsnctf/plugin/js/cvencode.js
qsnctf/plugin/js/jsfuck_decode.js
qsnctf/plugin/js/jsfuck_encode.js
qsnctf/plugin/python/operation.py
qsnctf/plugin/python/__pycache__/operation.cpython-311.pyc
qsnctf/plugin/python/python3base92/__init__.py
qsnctf/plugin/python/python3base92/__pycache__/__init__.cpython-311.pyc
qsnctf/plugin/txt/dirs.txt
qsnctf/plugin/txt/domain.txt
qsnctf/plugin/txt/shell_weak_password.txt
qsnctf/plugin/txt/zippass.txt
qsnctf-0.0.9.2.dist-info/METADATA
qsnctf-0.0.9.2.dist-info/WHEEL
qsnctf-0.0.9.2.dist-info/top_level.txt
qsnctf-0.0.9.2.dist-info/RECORD
