Metadata-Version: 2.4
Name: qsnctf
Version: 0.0.9.2
Summary: 青少年CTF训练平台提供的Python软件包
Home-page: https://github.com/Moxin1044/qsnctf-python
Author: Moxin
Author-email: 1044631097@qq.com
License: MIT License
Requires-Dist: PyExecJS2
Requires-Dist: base58
Requires-Dist: requests
Requires-Dist: bs4
Requires-Dist: urllib3
Requires-Dist: rarfile
Requires-Dist: sympy
Dynamic: author
Dynamic: author-email
Dynamic: description
Dynamic: description-content-type
Dynamic: home-page
Dynamic: license
Dynamic: requires-dist
Dynamic: summary
